boring_package-1.0.2.dist-info/licenses/LICENSE
valentines_surprise/__init__.py
boring_package-1.0.2.dist-info/METADATA
boring_package-1.0.2.dist-info/WHEEL
boring_package-1.0.2.dist-info/entry_points.txt
boring_package-1.0.2.dist-info/top_level.txt
boring_package-1.0.2.dist-info/RECORD
